dynamet/app.py
dynamet/carbon_count.py
dynamet/carbon_labeling.py
dynamet/config_manager.py
dynamet/data_analysis.py
dynamet/dict_to_mat.py
dynamet/edit_data.py
dynamet/global_features_grouper.py
dynamet/helper_funs.py
dynamet/idms_metabolite_identifyer.py
dynamet/iso_corr.py
dynamet/labeling_plots.py
dynamet/minimal_module.py
dynamet/objects_check.py
dynamet/peakmaps2feature_tables.py
dynamet/peakmap_processing.py
dynamet/pipeline_configs.py
dynamet/pipeline_manager.py
dynamet/project_creator_dli.py
dynamet/run_pipeline.py
dynamet/sample_feature_grouper.py
dynamet/suitability_test.py
dynamet/version.py
dynamet/__init__.py
dynamet/docs/20141030DYNAMET DOCUMENTATION.htm
dynamet/docs/~$141030DYNAMET DOCUMENTATION.htm
dynamet/docs/20141030DYNAMET DOCUMENTATION_files/colorschememapping.xml
dynamet/docs/20141030DYNAMET DOCUMENTATION_files/filelist.xml
dynamet/docs/20141030DYNAMET DOCUMENTATION_files/header.htm
dynamet/docs/20141030DYNAMET DOCUMENTATION_files/image001.jpg
dynamet/docs/20141030DYNAMET DOCUMENTATION_files/image001.png
dynamet/docs/20141030DYNAMET DOCUMENTATION_files/image002.jpg
dynamet/docs/20141030DYNAMET DOCUMENTATION_files/image002.png
dynamet/docs/20141030DYNAMET DOCUMENTATION_files/image003.jpg
dynamet/docs/20141030DYNAMET DOCUMENTATION_files/image003.png
dynamet/docs/20141030DYNAMET DOCUMENTATION_files/image004.jpg
dynamet/docs/20141030DYNAMET DOCUMENTATION_files/image004.png
dynamet/docs/20141030DYNAMET DOCUMENTATION_files/image005.jpg
dynamet/docs/20141030DYNAMET DOCUMENTATION_files/image005.png
dynamet/docs/20141030DYNAMET DOCUMENTATION_files/image006.jpg
dynamet/docs/20141030DYNAMET DOCUMENTATION_files/image006.png
dynamet/docs/20141030DYNAMET DOCUMENTATION_files/image007.png
dynamet/docs/20141030DYNAMET DOCUMENTATION_files/image008.png
dynamet/docs/20141030DYNAMET DOCUMENTATION_files/image009.png
dynamet/docs/20141030DYNAMET DOCUMENTATION_files/image010.jpg
dynamet-2.5.0.dist-info/DESCRIPTION.rst
dynamet-2.5.0.dist-info/entry_points.txt
dynamet-2.5.0.dist-info/METADATA
dynamet-2.5.0.dist-info/metadata.json
dynamet-2.5.0.dist-info/RECORD
dynamet-2.5.0.dist-info/top_level.txt
dynamet-2.5.0.dist-info/WHEEL
