Metadata-Version: 2.0
Name: dynamet
Version: 2.5.0
Summary: Dynamet is fully automated pipeline for dynamic labeling data
Home-page: UNKNOWN
Author: Patrick Kiefer
Author-email: kiefer@micro.biol.ethz.ch
License: http://opensource.org/licenses/GPL-3.0
Platform: UNKNOWN
Requires-Dist: hires
Requires-Dist: pacer (==0.5.3)
